a_pandas_ex_image_tools/README.MD
a_pandas_ex_image_tools/__init__.py
a_pandas_ex_image_tools/requirements.txt
a_pandas_ex_image_tools/thirdparty.json
a_pandas_ex_image_tools-0.11.dist-info/LICENSE.rst
a_pandas_ex_image_tools-0.11.dist-info/METADATA
a_pandas_ex_image_tools-0.11.dist-info/WHEEL
a_pandas_ex_image_tools-0.11.dist-info/top_level.txt
a_pandas_ex_image_tools-0.11.dist-info/RECORD
