Metadata-Version: 2.1
Name: a-pandas-ex-image-tools
Version: 0.11
Summary: Uses pandas/numpy/numexpr for operations on pictures - very fast
Home-page: https://github.com/hansalemaos/a_pandas_ex_image_tools
Author: Johannes Fischer
Author-email: aulasparticularesdealemaosp@gmail.com
License: MIT
Keywords: pandas,OpenCV,cv2,images,pixels,detection
Classifier: Development Status :: 4 - Beta
Classifier: Programming Language :: Python :: 3 :: Only
Classifier: Programming Language :: Python :: 3.10
Classifier: Topic :: Software Development :: Libraries :: Python Modules
Classifier: Topic :: Utilities
License-File: LICENSE.rst
Requires-Dist: PrettyColorPrinter
Requires-Dist: Shapely
Requires-Dist: a-cv2-imshow-thread
Requires-Dist: a-cv-imwrite-imread-plus
Requires-Dist: a-pandas-ex-closest-color
Requires-Dist: a-pandas-ex-column-reduce
Requires-Dist: a-pandas-ex-enumerate-groups
Requires-Dist: a-pandas-ex-horizontal-explode
Requires-Dist: a-pandas-ex-lookupdict
Requires-Dist: a-pandas-ex-multiloc
Requires-Dist: a-pandas-ex-obj-into-cell
Requires-Dist: a-pandas-ex-plode-tool
Requires-Dist: a-pandas-ex-to-tuple
Requires-Dist: ansi
Requires-Dist: flatten-everything
Requires-Dist: flexible-partial
Requires-Dist: numexpr
Requires-Dist: numpy
Requires-Dist: opencv-python
Requires-Dist: pandas
Requires-Dist: scikit-learn
